[
  {
    "id": "inbetween",
    "title": "INBETWEEN",
    "oneLiner": "Liminal exploration with something following you.",
    "status": "Prototype",
    "release": "TBA",
    "platforms": [
      "Roblox"
    ],
    "genres": [
      "Horror",
      "Exploration"
    ],
    "description": "INBETWEEN is focused on atmosphere, readable spaces, and tight pacing. Replace this placeholder with your own description, feature bullets, and gallery images.",
    "links": [
      {
        "label": "Roblox",
        "href": "#"
      }
    ],
    "media": [
      {
        "src": "assets/img/placeholders/square.svg",
        "alt": "Render 1"
      },
      {
        "src": "assets/img/placeholders/square.svg",
        "alt": "Render 2"
      },
      {
        "src": "assets/img/placeholders/square.svg",
        "alt": "Render 3"
      }
    ]
  }
]
